meegsim/__init__.py
meegsim/_check.py
meegsim/configuration.py
meegsim/coupling.py
meegsim/coupling_graph.py
meegsim/location.py
meegsim/sensor_noise.py
meegsim/simulate.py
meegsim/snr.py
meegsim/source_groups.py
meegsim/sources.py
meegsim/utils.py
meegsim/viz.py
meegsim/waveform.py
meegsim-0.0.2.dist-info/METADATA
meegsim-0.0.2.dist-info/WHEEL
meegsim-0.0.2.dist-info/licenses/LICENSE
meegsim-0.0.2.dist-info/RECORD
