Metadata-Version: 2.4
Name: meegsim
Version: 0.0.2
Summary: Building blocks (waveforms, SNR, connectivity) for M/EEG simulations with MNE-Python
Project-URL: Homepage, https://github.com/ctrltz/meegsim
Project-URL: Documentation, https://meegsim.readthedocs.io/
Project-URL: Issues, https://github.com/ctrltz/meegsim/issues
Author: Alina Studenova, Mina Jamshidi Idaji
Author-email: Nikolai Kapralov <kapralov@cbs.mpg.de>
License-File: LICENSE
Keywords: EEG,MEG,connectivity,simulation
Classifier: Development Status :: 3 - Alpha
Classifier: Intended Audience :: Science/Research
Classifier: License :: OSI Approved :: BSD License
Classifier: Operating System :: OS Independent
Classifier: Programming Language :: Python :: 3
Classifier: Topic :: Scientific/Engineering
Requires-Python: >=3.9
Requires-Dist: colorednoise
Requires-Dist: mne
Requires-Dist: networkx
Requires-Dist: nibabel
Provides-Extra: deploy
Requires-Dist: build; extra == 'deploy'
Requires-Dist: twine; extra == 'deploy'
Provides-Extra: dev
Requires-Dist: build; extra == 'dev'
Requires-Dist: darkdetect; extra == 'dev'
Requires-Dist: harmoni; extra == 'dev'
Requires-Dist: intersphinx-registry; extra == 'dev'
Requires-Dist: mock; extra == 'dev'
Requires-Dist: myst-parser; extra == 'dev'
Requires-Dist: neurodsp; extra == 'dev'
Requires-Dist: numpydoc; extra == 'dev'
Requires-Dist: pre-commit; extra == 'dev'
Requires-Dist: pydata-sphinx-theme; extra == 'dev'
Requires-Dist: pyqt6!=6.6.0; extra == 'dev'
Requires-Dist: pyqt6-qt6!=6.6.0,!=6.7.0; extra == 'dev'
Requires-Dist: pytest; extra == 'dev'
Requires-Dist: pytest-cov; extra == 'dev'
Requires-Dist: pyvista!=0.35.2,!=0.38.0,!=0.38.1,!=0.38.2,!=0.38.3,!=0.38.4,!=0.38.5,!=0.38.6,!=0.42.0,>=0.32; extra == 'dev'
Requires-Dist: pyvistaqt>=0.4; extra == 'dev'
Requires-Dist: ruff; extra == 'dev'
Requires-Dist: sphinx; extra == 'dev'
Requires-Dist: sphinx-copybutton; extra == 'dev'
Requires-Dist: sphinx-gallery; extra == 'dev'
Requires-Dist: sphinxcontrib-bibtex; extra == 'dev'
Requires-Dist: twine; extra == 'dev'
Provides-Extra: docs
Requires-Dist: harmoni; extra == 'docs'
Requires-Dist: intersphinx-registry; extra == 'docs'
Requires-Dist: myst-parser; extra == 'docs'
Requires-Dist: neurodsp; extra == 'docs'
Requires-Dist: numpydoc; extra == 'docs'
Requires-Dist: pydata-sphinx-theme; extra == 'docs'
Requires-Dist: sphinx; extra == 'docs'
Requires-Dist: sphinx-copybutton; extra == 'docs'
Requires-Dist: sphinx-gallery; extra == 'docs'
Requires-Dist: sphinxcontrib-bibtex; extra == 'docs'
Provides-Extra: plot
Requires-Dist: darkdetect; extra == 'plot'
Requires-Dist: pyqt6!=6.6.0; extra == 'plot'
Requires-Dist: pyqt6-qt6!=6.6.0,!=6.7.0; extra == 'plot'
Requires-Dist: pyvista!=0.35.2,!=0.38.0,!=0.38.1,!=0.38.2,!=0.38.3,!=0.38.4,!=0.38.5,!=0.38.6,!=0.42.0,>=0.32; extra == 'plot'
Requires-Dist: pyvistaqt>=0.4; extra == 'plot'
Provides-Extra: test
Requires-Dist: harmoni; extra == 'test'
Requires-Dist: mock; extra == 'test'
Requires-Dist: pre-commit; extra == 'test'
Requires-Dist: pytest; extra == 'test'
Requires-Dist: pytest-cov; extra == 'test'
Requires-Dist: ruff; extra == 'test'
